mtmai/__init__.py
mtmai/_version.py
mtmai/auth.py
mtmai/config.example.toml
mtmai/deps.py
mtmai/gradio_app.py
mtmai/hatchet.py
mtmai/hello_f2.py
mtmai/hello_g4f.py
mtmai/hello_h.py
mtmai/main.py
mtmai/middleware.py--
mtmai/mtm_engine.py
mtmai/otel.py
mtmai/run_event_listener.py
mtmai/server.py
mtmai/trace.py
mtmai/worker_app.py
mtmai/workflow.py
mtmai/workflow_listener.py
mtmai/workflow_run.py
mtmai/ws_worker.py
mtmai/用例.md
mtmai/agents/_mtbase_agent.py
mtmai/agents/assistant_agent.py
mtmai/agents/content_writer_agent.py
mtmai/agents/extract_page_data_agent.py
mtmai/agents/extract_page_data_agent_prompt.py
mtmai/agents/instagram_agent.py
mtmai/agents/page_script.js
mtmai/agents/tenant_agent.py
mtmai/agents/topic_writer_agent.py
mtmai/agents/webSurfer.py
mtmai/agents/adk_book_writer/__init__.py
mtmai/agents/adk_book_writer/book_writer_agent.py
mtmai/agents/adk_brand_search_optimization/__init__.py
mtmai/agents/adk_brand_search_optimization/agent.py
mtmai/agents/adk_brand_search_optimization/prompt.py
mtmai/agents/adk_brand_search_optimization/shared_libraries/constants.py
mtmai/agents/adk_brand_search_optimization/sub_agents/__init__.py
mtmai/agents/adk_brand_search_optimization/sub_agents/comparison/agent.py
mtmai/agents/adk_brand_search_optimization/sub_agents/comparison/prompt.py
mtmai/agents/adk_brand_search_optimization/sub_agents/keyword_finding/agent.py
mtmai/agents/adk_brand_search_optimization/sub_agents/keyword_finding/prompt.py
mtmai/agents/adk_brand_search_optimization/sub_agents/search_results/agent.py
mtmai/agents/adk_brand_search_optimization/sub_agents/search_results/prompt.py
mtmai/agents/adk_custom_agent/__init__.py
mtmai/agents/adk_custom_agent/adk_custom_agent.py
mtmai/agents/adk_smolagent/__init__.py
mtmai/agents/adk_smolagent/adk_smolagent.py
mtmai/agents/adk_smolagent/用例.md
mtmai/agents/adk_smolagent_blogwriter/adk_smolagent_blogwriter.py
mtmai/agents/agno/__init__.py
mtmai/agents/agno/agent_team.py
mtmai/agents/agno/blog_post_generator.py
mtxai-0.7.0.dist-info/METADATA
mtxai-0.7.0.dist-info/WHEEL
mtxai-0.7.0.dist-info/entry_points.txt
mtxai-0.7.0.dist-info/RECORD
